crio/UDP.py
crio/__init__.py
crio/crio.py
crio/getBenchIni.py
crio/iniconfig.cfg
crio/Loadini/Loadini.py
crio/Loadini/__init__.py
crio/config/__init__.py
crio/crio_hs/__init__.py
crio/crio_hs/crio_hs.py
crio/inis/__init__.py
crio-0.0.8.dist-info/LICENSE
crio-0.0.8.dist-info/METADATA
crio-0.0.8.dist-info/WHEEL
crio-0.0.8.dist-info/top_level.txt
crio-0.0.8.dist-info/RECORD
