Metadata-Version: 2.1
Name: crio
Version: 0.0.8
Summary: library for CRIO operation
License: Copyright (c) 2018 The Python Packaging Authority
Classifier: Programming Language :: Python :: 3
Classifier: License :: OSI Approved :: MIT License
Classifier: Operating System :: OS Independent
Requires-Python: >=3.7
License-File: LICENSE
